Metadata-Version: 1.1
Name: slogger
Version: 1.0.0
Summary: slogger is a dead simple logger to use. It can be configured in very easy way.
Home-page: https://github.com/cao5zy/slogger
Author: Zongying Cao
Author-email: zongying.cao@dxc.com
License: MIT
Platform: UNKNOWN
Classifier: Development Status :: 4 - Beta
Classifier: Intended Audience :: Developers
Classifier: License :: OSI Approved :: Apache Software License
Classifier: Natural Language :: English
Classifier: Operating System :: OS Independent
Classifier: Programming Language :: Python :: 3
Classifier: Topic :: Software Development :: Libraries
